fast_cd_pyb.cpython-310-darwin.so
fast_cody/fast_cd_sim.py
fast_cody/world2rel.py
fast_cody/momentum_leaking_matrix.py
fast_cody/read_msh.py
fast_cody/orthonormalize.py
fast_cody/one_euro_filter.py
fast_cody/cluster_grouping_matrices.py
fast_cody/rig_geometry.py
fast_cody/linear_elasticity_hessian.py
fast_cody/project_out_subspace.py
fast_cody/eigs.py
fast_cody/rotate_rig.py
fast_cody/__init__.py
fast_cody/umfpack_lu_solve.py
fast_cody/cluster_centroids.py
fast_cody/laplacian.py
fast_cody/normalize_height_and_center.py
fast_cody/vectorized_trace.py
fast_cody/skinning_clusters.py
fast_cody/diffuse_weights.py
fast_cody/skinning_subspace.py
fast_cody/complementary_constraint_matrix.py
fast_cody/read_rig_from_json.py
fast_cody/vectorized_transpose.py
fast_cody/deformation_jacobian.py
fast_cody/laplacian_eigenmodes.py
fast_cody/average_onto_simplex.py
fast_cody/project_into_subspace.py
fast_cody/rig_curve_geometry.py
fast_cody/ympr_to_lame.py
fast_cody/lbs_weight_space_constraint.py
fast_cody/arap_hessian.py
fast_cody/lbs_jacobian.py
fast_cody/closest_orthogonal_subspace.py
fast_cody/read_rig_anim_from_json.py
fast_cody/mediapipe_face_captor.py
fast_cody/viewers/WeightsViewer.py
fast_cody/viewers/ClustersViewer.py
fast_cody/viewers/__init__.py
fast_cody/viewers/interactive_handle_subspace_viewer.py
fast_cody/shaders/__init__.py
fast_cody/shaders/fragment_shader.glsl
fast_cody/shaders/vertex_shader_4.glsl
fast_cody/shaders/vertex_shader_8.glsl
fast_cody/shaders/vertex_shader_16.glsl
fast_cody/data/cd_fish_tex.png
fast_cody/data/cd_fish_tex.obj
fast_cody/data/__init__.py
fast_cody/data/cd_fish_rig_anim__swim.json
fast_cody/data/cd_fish_rig_anim__swim_speed_0.85.json
fast_cody/data/cd_fish.msh
fast_cody/data/cd_fish_rig.json
fast_cody/apps/interactive_cd_rig_anim.py
fast_cody/apps/interactive_cd_affine_handle.py
fast_cody/apps/__init__.py
fast_cody/apps/interactive_cd_face_tracking.py
fast_cody-0.0.8.dist-info/RECORD
fast_cody-0.0.8.dist-info/LICENSE
fast_cody-0.0.8.dist-info/WHEEL
fast_cody-0.0.8.dist-info/top_level.txt
fast_cody-0.0.8.dist-info/METADATA
