Metadata-Version: 2.1
Name: fast-cody
Version: 0.0.8
Home-page: https://github.com/otmanon/fast-cody/
Author: Otman Benchekroun
Author-email: otmanbench@gmail.com
License: MIT
License-File: LICENSE
Requires-Dist: packaging
Requires-Dist: numpy
Requires-Dist: scipy
Requires-Dist: mediapipe
Requires-Dist: opencv-python
Requires-Dist: cvxopt
Requires-Dist: polyscope
Requires-Dist: libigl
Requires-Dist: scikit-learn
